LICENSE
README.md
setup.py
zhcode/__init__.py
zhcode/helper.py
zhcode/main.py
zhcode.egg-info/PKG-INFO
zhcode.egg-info/SOURCES.txt
zhcode.egg-info/dependency_links.txt
zhcode.egg-info/top_level.txt
zhcode/python/__init__.py
zhcode/python/helper.py
zhcode/python/stdlib.py
zhcode/python/translate.py