Metadata-Version: 2.1
Name: zhcode
Version: 0.0.5
Summary: Programming languages in Chinese.
Home-page: https://github.com/Injng/zhcode
Author: lnjng
License: MIT
License-File: LICENSE
